ima/__init__.py
ima/__main__.py
ima/exceptions.py
ima/image.py
ima/options.py
ima/search.py
ima/utils.py
ima/version.py
ima_search-0.2.dist-info/LICENSE.txt
ima_search-0.2.dist-info/METADATA
ima_search-0.2.dist-info/WHEEL
ima_search-0.2.dist-info/entry_points.txt
ima_search-0.2.dist-info/top_level.txt
ima_search-0.2.dist-info/RECORD
