Metadata-Version: 2.1
Name: ima-search
Version: 0.2
Summary: Image searcher and downloader
Home-page: https://github.com/tcheukueppo/ima/
Author: tcheukueppo
Author-email: tcheukueppo@tutanota.com
License: GPL-3.0-only
Platform: any
Classifier: Development Status :: 4 - Beta
Classifier: Programming Language :: Python
Requires-Python: >=3.10
License-File: LICENSE.txt
Requires-Dist: requests
Requires-Dist: bs4
Requires-Dist: ansi
Requires-Dist: importlib-metadata ; python_version < "3.8"
Provides-Extra: testing
Requires-Dist: setuptools ; extra == 'testing'
Requires-Dist: pytest ; extra == 'testing'
Requires-Dist: pytest-cov ; extra == 'testing'
